dp3/__init__.py
dp3/worker.py
dp3/api/README.md
dp3/api/__init__.py
dp3/api/main.py
dp3/api/internal/__init__.py
dp3/api/internal/config.py
dp3/api/internal/dp_logger.py
dp3/api/internal/entity_response_models.py
dp3/api/internal/helpers.py
dp3/api/internal/models.py
dp3/api/internal/response_models.py
dp3/api/routers/__init__.py
dp3/api/routers/control.py
dp3/api/routers/entity.py
dp3/api/routers/root.py
dp3/api/routers/telemetry.py
dp3/bin/__init__.py
dp3/bin/api.py
dp3/bin/check.py
dp3/bin/cli.py
dp3/bin/config.py
dp3/bin/schema_update.py
dp3/bin/setup.py
dp3/bin/worker.py
dp3/common/__init__.py
dp3/common/attrspec.py
dp3/common/base_module.py
dp3/common/callback_registrar.py
dp3/common/config.py
dp3/common/context.py
dp3/common/control.py
dp3/common/datapoint.py
dp3/common/datatype.py
dp3/common/entityspec.py
dp3/common/mac_address.py
dp3/common/scheduler.py
dp3/common/state.py
dp3/common/task.py
dp3/common/types.py
dp3/common/utils.py
dp3/core/__init__.py
dp3/core/collector.py
dp3/core/link_manager.py
dp3/core/updater.py
dp3/database/__init__.py
dp3/database/config.py
dp3/database/database.py
dp3/database/encodings.py
dp3/database/exceptions.py
dp3/database/magic.py
dp3/database/schema_cleaner.py
dp3/database/snapshots.py
dp3/history_management/__init__.py
dp3/history_management/history_manager.py
dp3/history_management/telemetry.py
dp3/scripts/__init__.py
dp3/scripts/add_hashes.py
dp3/scripts/add_min_t2s.py
dp3/scripts/datapoint_log_converter.py
dp3/scripts/dummy_sender.py
dp3/scripts/migrate_snapshots.py
dp3/scripts/rmq_reconfigure.sh
dp3/scripts/script_runner.py
dp3/snapshots/__init__.py
dp3/snapshots/snapshooter.py
dp3/snapshots/snapshot_hooks.py
dp3/task_processing/__init__.py
dp3/task_processing/task_distributor.py
dp3/task_processing/task_executor.py
dp3/task_processing/task_hooks.py
dp3/task_processing/task_queue.py
dp3/template/appctl
dp3/template/app/README.md
dp3/template/app/docker-compose.app.yml
dp3/template/app/docker-compose.yml
dp_cubed-0.10.0.dist-info/licenses/LICENSE
dp_cubed-0.10.0.dist-info/METADATA
dp_cubed-0.10.0.dist-info/WHEEL
dp_cubed-0.10.0.dist-info/entry_points.txt
dp_cubed-0.10.0.dist-info/top_level.txt
dp_cubed-0.10.0.dist-info/RECORD
