Metadata-Version: 2.4
Name: dp-cubed
Version: 0.10.0
Summary: Dynamic Profile Processing Platform
Author: Vaclav Bartos
Author-email: bartos@cesnet.cz
License: COPYRIGHT AND PERMISSION NOTICE
Project-URL: Homepage, https://github.com/CESNET/dp3
Project-URL: Repository, https://github.com/CESNET/dp3
Project-URL: Documentation, https://cesnet.github.io/dp3
Classifier: Programming Language :: Python :: 3
Classifier: License :: OSI Approved :: BSD License
Classifier: Operating System :: OS Independent
Classifier: Development Status :: 3 - Alpha
Classifier: Framework :: FastAPI
Classifier: Framework :: Pydantic :: 1
Classifier: Topic :: Software Development :: Libraries :: Application Frameworks
Classifier: Topic :: Software Development :: Libraries :: Python Modules
Classifier: Intended Audience :: Developers
Requires-Python: >=3.9
License-File: LICENSE
Requires-Dist: AMQPStorm~=2.7.2
Requires-Dist: apscheduler~=3.10.0
Requires-Dist: event-count-logger>=1.1
Requires-Dist: fastapi>=0.109.1
Requires-Dist: pydantic>=2.4.0
Requires-Dist: pymongo~=4.6.3
Requires-Dist: python-dateutil~=2.8
Requires-Dist: pyyaml~=6.0
Requires-Dist: requests~=2.32.0
Requires-Dist: uvicorn>=0.22.0
Provides-Extra: dev
Requires-Dist: mkdocs>=1.0.3; extra == "dev"
Requires-Dist: mkdocs-gen-files>=0.4; extra == "dev"
Requires-Dist: mkdocs-literate-nav>=0.6; extra == "dev"
Requires-Dist: mkdocs-material>=9.0; extra == "dev"
Requires-Dist: mkdocs-section-index>=0.3; extra == "dev"
Requires-Dist: mkdocstrings>=0.19; extra == "dev"
Requires-Dist: mkdocstrings-python>=0.8; extra == "dev"
Requires-Dist: pre-commit~=3.0; extra == "dev"
Provides-Extra: deploy
Requires-Dist: gunicorn>=20.1; extra == "deploy"
Provides-Extra: scripts
Requires-Dist: numpy>=1.23.0; extra == "scripts"
Requires-Dist: pandas~=1.4.3; extra == "scripts"
Dynamic: license-file
